hhb/__init__.py
hhb/__main__.py
hhb/benchmark.py
hhb/codegen.py
hhb/importer.py
hhb/llm_api.py
hhb/main.py
hhb/profiler.py
hhb/quantizer.py
hhb/simulate.py
hhb/analysis/__init__.py
hhb/analysis/trace.py
hhb/config/c906.tp
hhb/config/c920.tp
hhb/config/th1520.tp
hhb/config/th1520_jit.tp
hhb/config/process/include/io.h
hhb/config/process/include/process.h
hhb/config/process/src/io.c
hhb/config/process/src/process.c
hhb/config/template/function_decl.tp
hhb/config/template/global_var_decl.tp
hhb/config/template/header.tp
hhb/config/template/macro_def.tp
hhb/config/template/makefile.tp
hhb/config/template/postprocess_def.tp
hhb/config/template/preprocess_def.tp
hhb/config/template/utils_def.tp
hhb/config/wrapper/device_exe.sh
hhb/config/wrapper/hhb_runtime_aot_cross_compile.sh
hhb/config/wrapper/hhb_runtime_device_aot.cc.tp
hhb/config/wrapper/hhb_runtime_device_aot.py.tp
hhb/config/wrapper/libtvm_runtime.so
hhb/config/wrapper/model_client.py
hhb/config/wrapper/model_server.py
hhb/config/wrapper/model_wrapper.py
hhb/config/wrapper/model_wrapper.tp
hhb/core/__init__.py
hhb/core/arguments_manage.py
hhb/core/codegen_manage.py
hhb/core/common.py
hhb/core/data_process.py
hhb/core/frontend_manage.py
hhb/core/hhbir_manage.py
hhb/core/legalize_ops.py
hhb/core/llm_manage.py
hhb/core/main_command_manage.py
hhb/core/preprocess_manage.py
hhb/core/profiler_manage.py
hhb/core/quantization_manage.py
hhb/core/schedules.py
hhb/core/simulate_manage.py
hhb/install_nn2/version
hhb/install_nn2/c906/include/shl_debug.h
hhb/install_nn2/c906/include/shl_memory.h
hhb/install_nn2/c906/include/shl_multithread.h
hhb/install_nn2/c906/include/shl_profiler.h
hhb/install_nn2/c906/include/shl_utils.h
hhb/install_nn2/c906/include/csinn/csi_nn.h
hhb/install_nn2/c906/include/csinn/csinn_data_structure.h
hhb/install_nn2/c906/include/csinn/csinn_runtime.h
hhb/install_nn2/c906/include/graph/shl_gref.h
hhb/install_nn2/c906/include/graph/shl_node.h
hhb/install_nn2/c906/include/shl_public/shl_c906.h
hhb-3.2.3.dist-info/METADATA
hhb-3.2.3.dist-info/WHEEL
hhb-3.2.3.dist-info/entry_points.txt
hhb-3.2.3.dist-info/top_level.txt
hhb-3.2.3.dist-info/RECORD
